brassica/__init__.py
brassica/brassica.py
brassica/BASIC/__init__.py
brassica/BASIC/animal.bas
brassica/BASIC/camel.bas
brassica/BASIC/chase.bas
brassica/BASIC/eliza.bas
brassica/BASIC/even wins.bas
brassica/BASIC/even_wins.bas
brassica/BASIC/evenwins.bas
brassica/BASIC/flip.bas
brassica/BASIC/four in a row.bas
brassica/BASIC/four_in_a_row.bas
brassica/BASIC/fourinarow.bas
brassica/BASIC/guess-it.bas
brassica/BASIC/guessit.bas
brassica/BASIC/hammurabi.bas
brassica/BASIC/hexapawn.bas
brassica/BASIC/inkblot.bas
brassica/BASIC/life.bas
brassica/BASIC/maze.bas
brassica/BASIC/not one.bas
brassica/BASIC/not_one.bas
brassica/BASIC/notone.bas
brassica/BASIC/seabattle.bas
brassica/BASIC/super_star_trek.bas
brassica/BASIC/superstartrek.bas
brassica/BASIC/wumpus.bas
brassica-1.0.2.dist-info/LICENSE
brassica-1.0.2.dist-info/METADATA
brassica-1.0.2.dist-info/WHEEL
brassica-1.0.2.dist-info/top_level.txt
brassica-1.0.2.dist-info/zip-safe
brassica-1.0.2.dist-info/RECORD
